{
    "Impostazioni": "Settings",
    "Salva modifiche": "Save Changes",
    "Salva": "Save",
    "Annulla": "Cancel",
    "Elimina": "Delete",
    "Modifica": "Edit",
    "Aggiungi": "Add",
    "Carica": "Upload",
    "Scarica": "Download",
    "Cerca": "Search",
    "Filtra": "Filter",
    "Aggiorna": "Update",
    "Ripristina": "Reset",
    "Attivo": "Active",
    "Disattivo": "Inactive",
    "In corso": "In Progress",
    "Completato": "Completed",
    "Errore": "Error",
    "Successo": "Success",
    "Fallito": "Failed",
    "Avviso": "Warning",
    "Video": "Video",
    "Trascrizione": "Transcription",
    "Descrizione": "Description",
    "Durata": "Duration",
    "Visualizzazioni": "Views",
    "Mi piace": "Likes",
    "Commenti": "Comments",
    "Data pubblicazione": "Publication Date",
    "Canale": "Channel",
    "Tag": "Tags",
    "Importa": "Import",
    "Esporta": "Export",
    "Elabora": "Process",
    "Genera": "Generate",
    "Rigenera": "Regenerate",
    "Sincronizza": "Synchronize",
    "Aggiorna dati": "Update Data",
    "Operazione completata con successo": "Operation completed successfully",
    "Si è verificato un errore": "An error occurred",
    "Nessun risultato trovato": "No results found",
    "Sei sicuro?": "Are you sure?",
    "Caricamento in corso": "Loading",
    "Attendere prego": "Please wait",
    "Coda": "Queue",
    "In coda": "Queued",
    "Elaborazione": "Processing",
    "Prossima esecuzione": "Next execution",
    "Video Pubblicati": "Published Videos",
    "Video in Bozza": "Draft Videos",
    "Totale Video": "Total Videos",
    "Statistiche": "Statistics"
}